BaseCanvas/__init__.py
BaseCanvas/base_canvas.py
base_canvas/__init__.py
base_canvas/base_canvas.py
base_canvas-1.0.7.dist-info/LICENSE
base_canvas-1.0.7.dist-info/METADATA
base_canvas-1.0.7.dist-info/WHEEL
base_canvas-1.0.7.dist-info/top_level.txt
base_canvas-1.0.7.dist-info/RECORD
