Metadata-Version: 2.1
Name: base-canvas
Version: 1.0.7
Summary: BaseCanvas is a small helper-class that handles common tasks in pygame.
Home-page: https://github.com/idJoca/BaseCanvas
Author: João Pedro Braz
Author-email: brazjoaopedro@ymail.com
License: UNKNOWN
Platform: UNKNOWN
Classifier: Programming Language :: Python :: 3
Classifier: License :: OSI Approved :: MIT License
Classifier: Operating System :: OS Independent
Requires-Python: >=3.7
Requires-Dist: pygame
